agentswarm/__init__.py
agentswarm/agents/__init__.py
agentswarm/agents/base_agent.py
agentswarm/cli/__init__.py
agentswarm/cli/main.py
agentswarm/cli/spec_manager.py
agentswarm/cli/task_parser.py
agentswarm/cli/task_utils.py
agentswarm/cli/commands/__init__.py
agentswarm/cli/commands/local.py
agentswarm/cli/commands/spec.py
agentswarm/cli/commands/task.py
agentswarm/core/__init__.py
agentswarm/core/agent_pool.py
agentswarm/core/config.py
agentswarm/core/models.py
agentswarm/core/orchestrator.py
agentswarm/core/state.py
agentswarm/lib/__init__.py
agentswarm/lib/distributed_cache.py
agentswarm/workflows/__init__.py
agentswarm/workflows/models.py
agentswarm/workflows/monitor.py
agentswarm/workflows/orchestrator.py
agentswarm/workflows/state.py
agentswarm/workflows/templates.py
multiagent_agentswarm/__init__.py
multiagent_agentswarm/cli.py
multiagent_agentswarm-1.2.1.dist-info/METADATA
multiagent_agentswarm-1.2.1.dist-info/WHEEL
multiagent_agentswarm-1.2.1.dist-info/entry_points.txt
multiagent_agentswarm-1.2.1.dist-info/top_level.txt
multiagent_agentswarm-1.2.1.dist-info/RECORD
