Metadata-Version: 2.4
Name: multiagent-agentswarm
Version: 1.2.1
Summary: Agent orchestration and swarm management for multi-agent development
Project-URL: Homepage, https://github.com/vanman2024/agentswarm
Project-URL: Issues, https://github.com/vanman2024/agentswarm/issues
Classifier: Development Status :: 4 - Beta
Classifier: Intended Audience :: Developers
Classifier: License :: OSI Approved :: MIT License
Classifier: Programming Language :: Python :: 3
Classifier: Programming Language :: Python :: 3.8
Classifier: Programming Language :: Python :: 3.9
Classifier: Programming Language :: Python :: 3.10
Classifier: Programming Language :: Python :: 3.11
Classifier: Programming Language :: Python :: 3.12
Requires-Python: >=3.8
Requires-Dist: multiagent-core>=0.1.0
Requires-Dist: click>=8.0.0
Requires-Dist: rich>=10.0.0
Requires-Dist: pyyaml>=6.0
Requires-Dist: requests>=2.25.0
